[
    {
        "name": "Diversity Cocktails at IROS",
        "date": "2023-10-03",
        "time": "7:00:00 PM",
        "region": "Americas",
        "location": " Firebird Tavern, 419 Monroe St, Detroit, MI 48226",
        "url": "https://ieee-iros.org/evening-socials/",
        "datetime": "2023-10-03T19:00:00"
    },
    {
        "name": "Bay Area - Building the Future with Women in Robotics",
        "date": "2023-10-04",
        "time": "5:30:00 PM",
        "region": "Americas",
        "location": null,
        "url": "https://www.eventbrite.com/e/building-the-future-with-women-in-robotics-tickets-720201481017",
        "datetime": "2023-10-04T17:30:00"
    }
]